{
    "1": {
        "board_size": 144,
        "obstacles": false,
        "population_size": 288,
        "generations": 100,
        "stepsize_param": 0.5,
        "crossover_rate": 0.9,
        "steps": 720,
        "best_fitness": -165708,
        "best_fitness_per_step": -230.15,
        "worst_fitness": -166278,
        "worst_fitness_per_step": -230.94166666666666,
        "average_fitness": -165946.42708333334,
        "average_fitness_per_step": -230.48114872685187,
        "best_attempted_moves": 720
    },
    "2": {
        "board_size": 144,
        "obstacles": false,
        "population_size": 288,
        "generations": 100,
        "stepsize_param": 0.5,
        "crossover_rate": 0.9,
        "steps": 720,
        "best_fitness": -165723,
        "best_fitness_per_step": -230.17083333333332,
        "worst_fitness": -166392,
        "worst_fitness_per_step": -231.1,
        "average_fitness": -165933.28125,
        "average_fitness_per_step": -230.462890625,
        "best_attempted_moves": 720
    },
    "3": {
        "board_size": 144,
        "obstacles": false,
        "population_size": 288,
        "generations": 100,
        "stepsize_param": 0.5,
        "crossover_rate": 0.9,
        "steps": 720,
        "best_fitness": -165690,
        "best_fitness_per_step": -230.125,
        "worst_fitness": -166227,
        "worst_fitness_per_step": -230.87083333333334,
        "average_fitness": -165935.69791666666,
        "average_fitness_per_step": -230.46624710648146,
        "best_attempted_moves": 720
    },
    "4": {
        "board_size": 144,
        "obstacles": false,
        "population_size": 288,
        "generations": 100,
        "stepsize_param": 0.5,
        "crossover_rate": 0.9,
        "steps": 720,
        "best_fitness": -165711,
        "best_fitness_per_step": -230.15416666666667,
        "worst_fitness": -166206,
        "worst_fitness_per_step": -230.84166666666667,
        "average_fitness": -165935.72916666666,
        "average_fitness_per_step": -230.46629050925924,
        "best_attempted_moves": 720
    },
    "5": {
        "board_size": 144,
        "obstacles": false,
        "population_size": 288,
        "generations": 100,
        "stepsize_param": 0.5,
        "crossover_rate": 0.9,
        "steps": 720,
        "best_fitness": -165738,
        "best_fitness_per_step": -230.19166666666666,
        "worst_fitness": -166242,
        "worst_fitness_per_step": -230.89166666666668,
        "average_fitness": -165933.64583333334,
        "average_fitness_per_step": -230.46339699074076,
        "best_attempted_moves": 720
    },
    "6": {
        "board_size": 144,
        "obstacles": false,
        "population_size": 288,
        "generations": 100,
        "stepsize_param": 0.5,
        "crossover_rate": 0.9,
        "steps": 720,
        "best_fitness": -165732,
        "best_fitness_per_step": -230.18333333333334,
        "worst_fitness": -166326,
        "worst_fitness_per_step": -231.00833333333333,
        "average_fitness": -165935.125,
        "average_fitness_per_step": -230.46545138888888,
        "best_attempted_moves": 720
    },
    "7": {
        "board_size": 144,
        "obstacles": false,
        "population_size": 288,
        "generations": 100,
        "stepsize_param": 0.5,
        "crossover_rate": 0.9,
        "steps": 720,
        "best_fitness": -165714,
        "best_fitness_per_step": -230.15833333333333,
        "worst_fitness": -166266,
        "worst_fitness_per_step": -230.925,
        "average_fitness": -165936.0625,
        "average_fitness_per_step": -230.46675347222222,
        "best_attempted_moves": 720
    },
    "8": {
        "board_size": 144,
        "obstacles": false,
        "population_size": 288,
        "generations": 100,
        "stepsize_param": 0.5,
        "crossover_rate": 0.9,
        "steps": 720,
        "best_fitness": -165699,
        "best_fitness_per_step": -230.1375,
        "worst_fitness": -166269,
        "worst_fitness_per_step": -230.92916666666667,
        "average_fitness": -165934.125,
        "average_fitness_per_step": -230.4640625,
        "best_attempted_moves": 720
    },
    "9": {
        "board_size": 144,
        "obstacles": false,
        "population_size": 288,
        "generations": 100,
        "stepsize_param": 0.5,
        "crossover_rate": 0.9,
        "steps": 720,
        "best_fitness": -165711,
        "best_fitness_per_step": -230.15416666666667,
        "worst_fitness": -166182,
        "worst_fitness_per_step": -230.80833333333334,
        "average_fitness": -165935.54166666666,
        "average_fitness_per_step": -230.46603009259258,
        "best_attempted_moves": 720
    },
    "10": {
        "board_size": 144,
        "obstacles": false,
        "population_size": 288,
        "generations": 100,
        "stepsize_param": 0.5,
        "crossover_rate": 0.9,
        "steps": 720,
        "best_fitness": -165720,
        "best_fitness_per_step": -230.16666666666666,
        "worst_fitness": -166185,
        "worst_fitness_per_step": -230.8125,
        "average_fitness": -165935.80208333334,
        "average_fitness_per_step": -230.4663917824074,
        "best_attempted_moves": 720
    },
    "11": {
        "board_size": 144,
        "obstacles": false,
        "population_size": 288,
        "generations": 100,
        "stepsize_param": 0.5,
        "crossover_rate": 0.9,
        "steps": 720,
        "best_fitness": -165660,
        "best_fitness_per_step": -230.08333333333334,
        "worst_fitness": -166173,
        "worst_fitness_per_step": -230.79583333333332,
        "average_fitness": -165939.08333333334,
        "average_fitness_per_step": -230.4709490740741,
        "best_attempted_moves": 720
    },
    "12": {
        "board_size": 144,
        "obstacles": false,
        "population_size": 288,
        "generations": 100,
        "stepsize_param": 0.5,
        "crossover_rate": 0.9,
        "steps": 720,
        "best_fitness": -165699,
        "best_fitness_per_step": -230.1375,
        "worst_fitness": -166263,
        "worst_fitness_per_step": -230.92083333333332,
        "average_fitness": -165940.625,
        "average_fitness_per_step": -230.47309027777777,
        "best_attempted_moves": 720
    },
    "13": {
        "board_size": 144,
        "obstacles": false,
        "population_size": 288,
        "generations": 100,
        "stepsize_param": 0.5,
        "crossover_rate": 0.9,
        "steps": 720,
        "best_fitness": -165738,
        "best_fitness_per_step": -230.19166666666666,
        "worst_fitness": -166212,
        "worst_fitness_per_step": -230.85,
        "average_fitness": -165938.25,
        "average_fitness_per_step": -230.46979166666668,
        "best_attempted_moves": 720
    },
    "14": {
        "board_size": 144,
        "obstacles": false,
        "population_size": 288,
        "generations": 100,
        "stepsize_param": 0.5,
        "crossover_rate": 0.9,
        "steps": 720,
        "best_fitness": -165702,
        "best_fitness_per_step": -230.14166666666668,
        "worst_fitness": -166296,
        "worst_fitness_per_step": -230.96666666666667,
        "average_fitness": -165936.69791666666,
        "average_fitness_per_step": -230.46763599537036,
        "best_attempted_moves": 720
    },
    "15": {
        "board_size": 144,
        "obstacles": false,
        "population_size": 288,
        "generations": 100,
        "stepsize_param": 0.5,
        "crossover_rate": 0.9,
        "steps": 720,
        "best_fitness": -165729,
        "best_fitness_per_step": -230.17916666666667,
        "worst_fitness": -166260,
        "worst_fitness_per_step": -230.91666666666666,
        "average_fitness": -165934.15625,
        "average_fitness_per_step": -230.4641059027778,
        "best_attempted_moves": 720
    },
    "16": {
        "board_size": 144,
        "obstacles": false,
        "population_size": 288,
        "generations": 100,
        "stepsize_param": 0.5,
        "crossover_rate": 0.9,
        "steps": 720,
        "best_fitness": -165729,
        "best_fitness_per_step": -230.17916666666667,
        "worst_fitness": -166263,
        "worst_fitness_per_step": -230.92083333333332,
        "average_fitness": -165930.95833333334,
        "average_fitness_per_step": -230.45966435185187,
        "best_attempted_moves": 720
    },
    "17": {
        "board_size": 144,
        "obstacles": false,
        "population_size": 288,
        "generations": 100,
        "stepsize_param": 0.5,
        "crossover_rate": 0.9,
        "steps": 720,
        "best_fitness": -165705,
        "best_fitness_per_step": -230.14583333333334,
        "worst_fitness": -166410,
        "worst_fitness_per_step": -231.125,
        "average_fitness": -165933.22916666666,
        "average_fitness_per_step": -230.462818287037,
        "best_attempted_moves": 720
    },
    "18": {
        "board_size": 144,
        "obstacles": false,
        "population_size": 288,
        "generations": 100,
        "stepsize_param": 0.5,
        "crossover_rate": 0.9,
        "steps": 720,
        "best_fitness": -165714,
        "best_fitness_per_step": -230.15833333333333,
        "worst_fitness": -166227,
        "worst_fitness_per_step": -230.87083333333334,
        "average_fitness": -165940.66666666666,
        "average_fitness_per_step": -230.47314814814814,
        "best_attempted_moves": 720
    },
    "19": {
        "board_size": 144,
        "obstacles": false,
        "population_size": 288,
        "generations": 100,
        "stepsize_param": 0.5,
        "crossover_rate": 0.9,
        "steps": 720,
        "best_fitness": -165663,
        "best_fitness_per_step": -230.0875,
        "worst_fitness": -166227,
        "worst_fitness_per_step": -230.87083333333334,
        "average_fitness": -165939.65625,
        "average_fitness_per_step": -230.47174479166668,
        "best_attempted_moves": 720
    },
    "20": {
        "board_size": 144,
        "obstacles": false,
        "population_size": 288,
        "generations": 100,
        "stepsize_param": 0.5,
        "crossover_rate": 0.9,
        "steps": 720,
        "best_fitness": -165771,
        "best_fitness_per_step": -230.2375,
        "worst_fitness": -166305,
        "worst_fitness_per_step": -230.97916666666666,
        "average_fitness": -165938.57291666666,
        "average_fitness_per_step": -230.47024016203702,
        "best_attempted_moves": 720
    }
}